pyxl.pth
setup.cfg
setup.py
emacs/pyxl-mode.el
pyxl/__init__.py
pyxl/base.py
pyxl/browser_hacks.py
pyxl/element.py
pyxl/html.py
pyxl/rss.py
pyxl/utils.py
pyxl/codec/__init__.py
pyxl/codec/html_tokenizer.py
pyxl/codec/parser.py
pyxl/codec/pytokenize.py
pyxl/codec/register.py
pyxl/codec/tokenizer.py
pyxl/scripts/__init__.py
pyxl/scripts/parse_file.py
pyxl4.egg-info/PKG-INFO
pyxl4.egg-info/SOURCES.txt
pyxl4.egg-info/dependency_links.txt
pyxl4.egg-info/top_level.txt