Metadata-Version: 1.0
Name: pyxl4
Version: 1.0.0a1
Summary: Extend Python syntax with HTML.
Home-page: https://github.com/pyxl4/pyxl4
Author: Adam Serafini
Author-email: adam@adamserafini.com
License: UNKNOWN
Platform: UNKNOWN
